{
  "HybridFL": [
    {
      "gflops": 16689.59247,
      "accuracy": 15.710000038146973
    },
    {
      "gflops": 33379.18494,
      "accuracy": 22.81999969482422
    },
    {
      "gflops": 50068.77741,
      "accuracy": 11.600000381469727
    },
    {
      "gflops": 66758.36988,
      "accuracy": 23.40999984741211
    },
    {
      "gflops": 83447.96235,
      "accuracy": 24.149999618530273
    },
    {
      "gflops": 100137.55482,
      "accuracy": 24.6299991607666
    },
    {
      "gflops": 116827.14729,
      "accuracy": 20.6299991607666
    },
    {
      "gflops": 133516.73976,
      "accuracy": 27.670000076293945
    },
    {
      "gflops": 150206.33223,
      "accuracy": 30.770000457763672
    },
    {
      "gflops": 166895.9247,
      "accuracy": 29.709999084472656
    },
    {
      "gflops": 183585.51717,
      "accuracy": 31.34000015258789
    },
    {
      "gflops": 200275.10964,
      "accuracy": 26.280000686645508
    },
    {
      "gflops": 216964.70211,
      "accuracy": 35.689998626708984
    },
    {
      "gflops": 233654.29458,
      "accuracy": 38.81999969482422
    },
    {
      "gflops": 250343.88705,
      "accuracy": 32.04999923706055
    },
    {
      "gflops": 267033.47952,
      "accuracy": 34.630001068115234
    },
    {
      "gflops": 283723.07199,
      "accuracy": 38.040000915527344
    },
    {
      "gflops": 300412.66446,
      "accuracy": 37.7599983215332
    },
    {
      "gflops": 317102.25693,
      "accuracy": 44.66999816894531
    },
    {
      "gflops": 333791.8494,
      "accuracy": 37.599998474121094
    },
    {
      "gflops": 350481.44187,
      "accuracy": 37.150001525878906
    },
    {
      "gflops": 367171.03434,
      "accuracy": 39.790000915527344
    },
    {
      "gflops": 383860.62681,
      "accuracy": 41.189998626708984
    },
    {
      "gflops": 400550.21928,
      "accuracy": 41.86000061035156
    },
    {
      "gflops": 417239.81175,
      "accuracy": 36.279998779296875
    },
    {
      "gflops": 433929.40422,
      "accuracy": 47.04999923706055
    },
    {
      "gflops": 450618.99669,
      "accuracy": 40.209999084472656
    },
    {
      "gflops": 467308.58916,
      "accuracy": 42.0
    },
    {
      "gflops": 483998.18163,
      "accuracy": 46.900001525878906
    },
    {
      "gflops": 500687.7741,
      "accuracy": 44.290000915527344
    },
    {
      "gflops": 517377.36657,
      "accuracy": 36.619998931884766
    },
    {
      "gflops": 534066.95904,
      "accuracy": 44.310001373291016
    },
    {
      "gflops": 550756.55151,
      "accuracy": 43.349998474121094
    },
    {
      "gflops": 567446.14398,
      "accuracy": 40.400001525878906
    },
    {
      "gflops": 584135.73645,
      "accuracy": 48.95000076293945
    },
    {
      "gflops": 600825.32892,
      "accuracy": 43.02000045776367
    },
    {
      "gflops": 617514.92139,
      "accuracy": 44.45000076293945
    },
    {
      "gflops": 634204.51386,
      "accuracy": 42.970001220703125
    },
    {
      "gflops": 650894.10633,
      "accuracy": 43.5
    },
    {
      "gflops": 667583.6988,
      "accuracy": 37.77000045776367
    },
    {
      "gflops": 684273.29127,
      "accuracy": 43.779998779296875
    },
    {
      "gflops": 700962.88374,
      "accuracy": 44.63999938964844
    },
    {
      "gflops": 717652.47621,
      "accuracy": 42.40999984741211
    },
    {
      "gflops": 734342.06868,
      "accuracy": 41.779998779296875
    },
    {
      "gflops": 751031.66115,
      "accuracy": 40.58000183105469
    },
    {
      "gflops": 767721.25362,
      "accuracy": 43.459999084472656
    },
    {
      "gflops": 784410.84609,
      "accuracy": 43.52000045776367
    },
    {
      "gflops": 801100.43856,
      "accuracy": 42.58000183105469
    },
    {
      "gflops": 817790.03103,
      "accuracy": 36.459999084472656
    },
    {
      "gflops": 834479.6235,
      "accuracy": 44.119998931884766
    },
    {
      "gflops": 851169.21597,
      "accuracy": 45.45000076293945
    },
    {
      "gflops": 867858.80844,
      "accuracy": 44.119998931884766
    },
    {
      "gflops": 884548.40091,
      "accuracy": 46.68000030517578
    },
    {
      "gflops": 901237.99338,
      "accuracy": 47.81999969482422
    },
    {
      "gflops": 917927.58585,
      "accuracy": 44.0099983215332
    },
    {
      "gflops": 934617.17832,
      "accuracy": 45.380001068115234
    },
    {
      "gflops": 951306.77079,
      "accuracy": 45.380001068115234
    },
    {
      "gflops": 967996.36326,
      "accuracy": 43.7599983215332
    },
    {
      "gflops": 984685.95573,
      "accuracy": 45.560001373291016
    },
    {
      "gflops": 1001375.5482,
      "accuracy": 49.36000061035156
    },
    {
      "gflops": 1018065.14067,
      "accuracy": 47.88999938964844
    },
    {
      "gflops": 1034754.73314,
      "accuracy": 42.79999923706055
    },
    {
      "gflops": 1051444.32561,
      "accuracy": 44.810001373291016
    },
    {
      "gflops": 1068133.91808,
      "accuracy": 45.91999816894531
    },
    {
      "gflops": 1084823.51055,
      "accuracy": 46.099998474121094
    },
    {
      "gflops": 1101513.10302,
      "accuracy": 44.900001525878906
    },
    {
      "gflops": 1118202.69549,
      "accuracy": 45.83000183105469
    },
    {
      "gflops": 1134892.28796,
      "accuracy": 40.150001525878906
    },
    {
      "gflops": 1151581.88043,
      "accuracy": 46.83000183105469
    },
    {
      "gflops": 1168271.4729,
      "accuracy": 49.369998931884766
    },
    {
      "gflops": 1184961.06537,
      "accuracy": 43.65999984741211
    },
    {
      "gflops": 1201650.65784,
      "accuracy": 48.20000076293945
    },
    {
      "gflops": 1218340.25031,
      "accuracy": 43.400001525878906
    },
    {
      "gflops": 1235029.84278,
      "accuracy": 46.77000045776367
    },
    {
      "gflops": 1251719.43525,
      "accuracy": 48.689998626708984
    },
    {
      "gflops": 1268409.02772,
      "accuracy": 44.56999969482422
    },
    {
      "gflops": 1285098.62019,
      "accuracy": 47.650001525878906
    },
    {
      "gflops": 1301788.21266,
      "accuracy": 49.279998779296875
    },
    {
      "gflops": 1318477.80513,
      "accuracy": 41.97999954223633
    },
    {
      "gflops": 1335167.3976,
      "accuracy": 47.58000183105469
    },
    {
      "gflops": 1351856.99007,
      "accuracy": 46.20000076293945
    },
    {
      "gflops": 1368546.58254,
      "accuracy": 43.52000045776367
    },
    {
      "gflops": 1385236.17501,
      "accuracy": 47.95000076293945
    },
    {
      "gflops": 1401925.76748,
      "accuracy": 47.04999923706055
    },
    {
      "gflops": 1418615.35995,
      "accuracy": 39.15999984741211
    },
    {
      "gflops": 1435304.95242,
      "accuracy": 44.75
    },
    {
      "gflops": 1451994.54489,
      "accuracy": 47.36000061035156
    },
    {
      "gflops": 1468684.13736,
      "accuracy": 46.61000061035156
    },
    {
      "gflops": 1485373.72983,
      "accuracy": 45.470001220703125
    },
    {
      "gflops": 1502063.3223,
      "accuracy": 46.75
    },
    {
      "gflops": 1518752.91477,
      "accuracy": 44.209999084472656
    },
    {
      "gflops": 1535442.50724,
      "accuracy": 42.959999084472656
    },
    {
      "gflops": 1552132.09971,
      "accuracy": 48.970001220703125
    },
    {
      "gflops": 1568821.69218,
      "accuracy": 47.93000030517578
    },
    {
      "gflops": 1585511.28465,
      "accuracy": 48.88999938964844
    },
    {
      "gflops": 1602200.87712,
      "accuracy": 49.5
    },
    {
      "gflops": 1618890.46959,
      "accuracy": 46.88999938964844
    },
    {
      "gflops": 1635580.06206,
      "accuracy": 46.54999923706055
    },
    {
      "gflops": 1652269.65453,
      "accuracy": 47.810001373291016
    },
    {
      "gflops": 1668959.247,
      "accuracy": 47.619998931884766
    }
  ],
  "CLG-SGD": [
    {
      "gflops": 16689.59247,
      "accuracy": 25.75
    },
    {
      "gflops": 33379.18494,
      "accuracy": 29.309999465942383
    },
    {
      "gflops": 50068.77741,
      "accuracy": 35.0
    },
    {
      "gflops": 66758.36988,
      "accuracy": 28.81999969482422
    },
    {
      "gflops": 83447.96235,
      "accuracy": 39.38999938964844
    },
    {
      "gflops": 100137.55482,
      "accuracy": 39.22999954223633
    },
    {
      "gflops": 116827.14729,
      "accuracy": 37.560001373291016
    },
    {
      "gflops": 133516.73976,
      "accuracy": 43.880001068115234
    },
    {
      "gflops": 150206.33223,
      "accuracy": 40.7599983215332
    },
    {
      "gflops": 166895.9247,
      "accuracy": 43.900001525878906
    },
    {
      "gflops": 183585.51717,
      "accuracy": 42.439998626708984
    },
    {
      "gflops": 200275.10964,
      "accuracy": 45.13999938964844
    },
    {
      "gflops": 216964.70211,
      "accuracy": 45.2400016784668
    },
    {
      "gflops": 233654.29458,
      "accuracy": 44.619998931884766
    },
    {
      "gflops": 250343.88705,
      "accuracy": 43.779998779296875
    },
    {
      "gflops": 267033.47952,
      "accuracy": 44.70000076293945
    },
    {
      "gflops": 283723.07199,
      "accuracy": 44.439998626708984
    },
    {
      "gflops": 300412.66446,
      "accuracy": 45.18000030517578
    },
    {
      "gflops": 317102.25693,
      "accuracy": 44.70000076293945
    },
    {
      "gflops": 333791.8494,
      "accuracy": 44.560001373291016
    },
    {
      "gflops": 350481.44187,
      "accuracy": 44.79999923706055
    },
    {
      "gflops": 367171.03434,
      "accuracy": 44.540000915527344
    },
    {
      "gflops": 383860.62681,
      "accuracy": 45.18000030517578
    },
    {
      "gflops": 400550.21928,
      "accuracy": 45.220001220703125
    },
    {
      "gflops": 417239.81175,
      "accuracy": 44.93000030517578
    },
    {
      "gflops": 433929.40422,
      "accuracy": 44.720001220703125
    },
    {
      "gflops": 450618.99669,
      "accuracy": 45.040000915527344
    },
    {
      "gflops": 467308.58916,
      "accuracy": 45.369998931884766
    },
    {
      "gflops": 483998.18163,
      "accuracy": 45.5099983215332
    },
    {
      "gflops": 500687.7741,
      "accuracy": 45.33000183105469
    },
    {
      "gflops": 517377.36657,
      "accuracy": 46.130001068115234
    },
    {
      "gflops": 534066.95904,
      "accuracy": 45.290000915527344
    },
    {
      "gflops": 550756.55151,
      "accuracy": 45.90999984741211
    },
    {
      "gflops": 567446.14398,
      "accuracy": 45.900001525878906
    },
    {
      "gflops": 584135.73645,
      "accuracy": 46.0
    },
    {
      "gflops": 600825.32892,
      "accuracy": 45.380001068115234
    },
    {
      "gflops": 617514.92139,
      "accuracy": 45.709999084472656
    },
    {
      "gflops": 634204.51386,
      "accuracy": 46.0
    },
    {
      "gflops": 650894.10633,
      "accuracy": 46.29999923706055
    },
    {
      "gflops": 667583.6988,
      "accuracy": 46.33000183105469
    },
    {
      "gflops": 684273.29127,
      "accuracy": 45.93000030517578
    },
    {
      "gflops": 700962.88374,
      "accuracy": 45.779998779296875
    },
    {
      "gflops": 717652.47621,
      "accuracy": 47.040000915527344
    },
    {
      "gflops": 734342.06868,
      "accuracy": 46.380001068115234
    },
    {
      "gflops": 751031.66115,
      "accuracy": 46.38999938964844
    },
    {
      "gflops": 767721.25362,
      "accuracy": 45.970001220703125
    },
    {
      "gflops": 784410.84609,
      "accuracy": 45.630001068115234
    },
    {
      "gflops": 801100.43856,
      "accuracy": 46.790000915527344
    },
    {
      "gflops": 817790.03103,
      "accuracy": 47.45000076293945
    },
    {
      "gflops": 834479.6235,
      "accuracy": 47.720001220703125
    },
    {
      "gflops": 851169.21597,
      "accuracy": 46.65999984741211
    },
    {
      "gflops": 867858.80844,
      "accuracy": 47.11000061035156
    },
    {
      "gflops": 884548.40091,
      "accuracy": 47.29999923706055
    },
    {
      "gflops": 901237.99338,
      "accuracy": 47.220001220703125
    },
    {
      "gflops": 917927.58585,
      "accuracy": 47.93000030517578
    },
    {
      "gflops": 934617.17832,
      "accuracy": 47.7400016784668
    },
    {
      "gflops": 951306.77079,
      "accuracy": 48.459999084472656
    },
    {
      "gflops": 967996.36326,
      "accuracy": 47.36000061035156
    },
    {
      "gflops": 984685.95573,
      "accuracy": 47.70000076293945
    },
    {
      "gflops": 1001375.5482,
      "accuracy": 48.290000915527344
    },
    {
      "gflops": 1018065.14067,
      "accuracy": 47.84000015258789
    },
    {
      "gflops": 1034754.73314,
      "accuracy": 47.849998474121094
    },
    {
      "gflops": 1051444.32561,
      "accuracy": 47.119998931884766
    },
    {
      "gflops": 1068133.91808,
      "accuracy": 47.79999923706055
    },
    {
      "gflops": 1084823.51055,
      "accuracy": 47.779998779296875
    },
    {
      "gflops": 1101513.10302,
      "accuracy": 48.15999984741211
    },
    {
      "gflops": 1118202.69549,
      "accuracy": 47.93000030517578
    },
    {
      "gflops": 1134892.28796,
      "accuracy": 47.439998626708984
    },
    {
      "gflops": 1151581.88043,
      "accuracy": 47.619998931884766
    },
    {
      "gflops": 1168271.4729,
      "accuracy": 48.72999954223633
    },
    {
      "gflops": 1184961.06537,
      "accuracy": 48.099998474121094
    },
    {
      "gflops": 1201650.65784,
      "accuracy": 47.91999816894531
    },
    {
      "gflops": 1218340.25031,
      "accuracy": 49.09000015258789
    },
    {
      "gflops": 1235029.84278,
      "accuracy": 49.720001220703125
    },
    {
      "gflops": 1251719.43525,
      "accuracy": 48.38999938964844
    },
    {
      "gflops": 1268409.02772,
      "accuracy": 46.84000015258789
    },
    {
      "gflops": 1285098.62019,
      "accuracy": 47.02000045776367
    },
    {
      "gflops": 1301788.21266,
      "accuracy": 47.18000030517578
    },
    {
      "gflops": 1318477.80513,
      "accuracy": 47.68000030517578
    },
    {
      "gflops": 1335167.3976,
      "accuracy": 47.310001373291016
    },
    {
      "gflops": 1351856.99007,
      "accuracy": 48.47999954223633
    },
    {
      "gflops": 1368546.58254,
      "accuracy": 48.02000045776367
    },
    {
      "gflops": 1385236.17501,
      "accuracy": 47.689998626708984
    },
    {
      "gflops": 1401925.76748,
      "accuracy": 47.529998779296875
    },
    {
      "gflops": 1418615.35995,
      "accuracy": 48.959999084472656
    },
    {
      "gflops": 1435304.95242,
      "accuracy": 48.11000061035156
    },
    {
      "gflops": 1451994.54489,
      "accuracy": 47.869998931884766
    },
    {
      "gflops": 1468684.13736,
      "accuracy": 47.709999084472656
    },
    {
      "gflops": 1485373.72983,
      "accuracy": 49.25
    },
    {
      "gflops": 1502063.3223,
      "accuracy": 47.2599983215332
    },
    {
      "gflops": 1518752.91477,
      "accuracy": 49.15999984741211
    },
    {
      "gflops": 1535442.50724,
      "accuracy": 48.70000076293945
    },
    {
      "gflops": 1552132.09971,
      "accuracy": 48.40999984741211
    },
    {
      "gflops": 1568821.69218,
      "accuracy": 47.58000183105469
    },
    {
      "gflops": 1585511.28465,
      "accuracy": 47.15999984741211
    },
    {
      "gflops": 1602200.87712,
      "accuracy": 47.63999938964844
    },
    {
      "gflops": 1618890.46959,
      "accuracy": 47.599998474121094
    },
    {
      "gflops": 1635580.06206,
      "accuracy": 47.709999084472656
    },
    {
      "gflops": 1652269.65453,
      "accuracy": 48.439998626708984
    },
    {
      "gflops": 1668959.247,
      "accuracy": 48.650001525878906
    }
  ],
  "Fed-C": [
    {
      "gflops": 33379.18494,
      "accuracy": 28.190000534057617
    },
    {
      "gflops": 66758.36988,
      "accuracy": 32.0
    },
    {
      "gflops": 100137.55482,
      "accuracy": 36.209999084472656
    },
    {
      "gflops": 133516.73976,
      "accuracy": 39.06999969482422
    },
    {
      "gflops": 166895.9247,
      "accuracy": 35.54999923706055
    },
    {
      "gflops": 200275.10964,
      "accuracy": 37.79999923706055
    },
    {
      "gflops": 233654.29458,
      "accuracy": 35.459999084472656
    },
    {
      "gflops": 267033.47952,
      "accuracy": 37.2400016784668
    },
    {
      "gflops": 300412.66446,
      "accuracy": 42.5099983215332
    },
    {
      "gflops": 333791.8494,
      "accuracy": 44.540000915527344
    },
    {
      "gflops": 367171.03434,
      "accuracy": 42.869998931884766
    },
    {
      "gflops": 400550.21928,
      "accuracy": 44.459999084472656
    },
    {
      "gflops": 433929.40422,
      "accuracy": 44.79999923706055
    },
    {
      "gflops": 467308.58916,
      "accuracy": 45.880001068115234
    },
    {
      "gflops": 500687.7741,
      "accuracy": 45.7599983215332
    },
    {
      "gflops": 534066.95904,
      "accuracy": 45.880001068115234
    },
    {
      "gflops": 567446.14398,
      "accuracy": 45.5099983215332
    },
    {
      "gflops": 600825.32892,
      "accuracy": 44.689998626708984
    },
    {
      "gflops": 634204.51386,
      "accuracy": 45.04999923706055
    },
    {
      "gflops": 667583.6988,
      "accuracy": 44.77000045776367
    },
    {
      "gflops": 700962.88374,
      "accuracy": 44.18000030517578
    },
    {
      "gflops": 734342.06868,
      "accuracy": 45.209999084472656
    },
    {
      "gflops": 767721.25362,
      "accuracy": 44.400001525878906
    },
    {
      "gflops": 801100.43856,
      "accuracy": 44.70000076293945
    },
    {
      "gflops": 834479.6235,
      "accuracy": 44.43000030517578
    },
    {
      "gflops": 867858.80844,
      "accuracy": 44.15999984741211
    },
    {
      "gflops": 901237.99338,
      "accuracy": 45.060001373291016
    },
    {
      "gflops": 934617.17832,
      "accuracy": 44.599998474121094
    },
    {
      "gflops": 967996.36326,
      "accuracy": 43.88999938964844
    },
    {
      "gflops": 1001375.5482,
      "accuracy": 44.529998779296875
    },
    {
      "gflops": 1034754.73314,
      "accuracy": 45.02000045776367
    },
    {
      "gflops": 1068133.91808,
      "accuracy": 44.70000076293945
    },
    {
      "gflops": 1101513.10302,
      "accuracy": 44.9900016784668
    },
    {
      "gflops": 1134892.28796,
      "accuracy": 43.77000045776367
    },
    {
      "gflops": 1168271.4729,
      "accuracy": 45.06999969482422
    },
    {
      "gflops": 1201650.65784,
      "accuracy": 45.529998779296875
    },
    {
      "gflops": 1235029.84278,
      "accuracy": 44.66999816894531
    },
    {
      "gflops": 1268409.02772,
      "accuracy": 44.9900016784668
    },
    {
      "gflops": 1301788.21266,
      "accuracy": 45.0
    },
    {
      "gflops": 1335167.3976,
      "accuracy": 44.79999923706055
    },
    {
      "gflops": 1368546.58254,
      "accuracy": 44.66999816894531
    },
    {
      "gflops": 1401925.76748,
      "accuracy": 43.59000015258789
    },
    {
      "gflops": 1435304.95242,
      "accuracy": 44.619998931884766
    },
    {
      "gflops": 1468684.13736,
      "accuracy": 45.0
    },
    {
      "gflops": 1502063.3223,
      "accuracy": 44.97999954223633
    },
    {
      "gflops": 1535442.50724,
      "accuracy": 43.630001068115234
    },
    {
      "gflops": 1568821.69218,
      "accuracy": 44.58000183105469
    },
    {
      "gflops": 1602200.87712,
      "accuracy": 44.06999969482422
    },
    {
      "gflops": 1635580.06206,
      "accuracy": 44.439998626708984
    },
    {
      "gflops": 1668959.247,
      "accuracy": 44.65999984741211
    },
    {
      "gflops": 1702338.43194,
      "accuracy": 44.720001220703125
    },
    {
      "gflops": 1735717.61688,
      "accuracy": 44.38999938964844
    },
    {
      "gflops": 1769096.80182,
      "accuracy": 43.72999954223633
    },
    {
      "gflops": 1802475.98676,
      "accuracy": 44.41999816894531
    },
    {
      "gflops": 1835855.1717,
      "accuracy": 45.40999984741211
    },
    {
      "gflops": 1869234.35664,
      "accuracy": 44.06999969482422
    },
    {
      "gflops": 1902613.54158,
      "accuracy": 44.41999816894531
    },
    {
      "gflops": 1935992.72652,
      "accuracy": 44.81999969482422
    },
    {
      "gflops": 1969371.91146,
      "accuracy": 45.119998931884766
    },
    {
      "gflops": 2002751.0964,
      "accuracy": 44.650001525878906
    },
    {
      "gflops": 2036130.28134,
      "accuracy": 44.97999954223633
    },
    {
      "gflops": 2069509.46628,
      "accuracy": 45.31999969482422
    },
    {
      "gflops": 2102888.65122,
      "accuracy": 44.25
    },
    {
      "gflops": 2136267.83616,
      "accuracy": 45.400001525878906
    },
    {
      "gflops": 2169647.0211,
      "accuracy": 45.25
    },
    {
      "gflops": 2203026.20604,
      "accuracy": 43.41999816894531
    },
    {
      "gflops": 2236405.39098,
      "accuracy": 44.040000915527344
    },
    {
      "gflops": 2269784.57592,
      "accuracy": 44.2599983215332
    },
    {
      "gflops": 2303163.76086,
      "accuracy": 44.72999954223633
    },
    {
      "gflops": 2336542.9458,
      "accuracy": 44.93000030517578
    },
    {
      "gflops": 2369922.13074,
      "accuracy": 43.29999923706055
    },
    {
      "gflops": 2403301.31568,
      "accuracy": 46.02000045776367
    },
    {
      "gflops": 2436680.50062,
      "accuracy": 45.349998474121094
    },
    {
      "gflops": 2470059.68556,
      "accuracy": 45.650001525878906
    },
    {
      "gflops": 2503438.8705,
      "accuracy": 45.529998779296875
    },
    {
      "gflops": 2536818.05544,
      "accuracy": 44.779998779296875
    },
    {
      "gflops": 2570197.24038,
      "accuracy": 45.02000045776367
    },
    {
      "gflops": 2603576.42532,
      "accuracy": 44.86000061035156
    },
    {
      "gflops": 2636955.61026,
      "accuracy": 44.34000015258789
    },
    {
      "gflops": 2670334.7952,
      "accuracy": 44.02000045776367
    },
    {
      "gflops": 2703713.98014,
      "accuracy": 43.720001220703125
    },
    {
      "gflops": 2737093.16508,
      "accuracy": 44.810001373291016
    },
    {
      "gflops": 2770472.35002,
      "accuracy": 44.90999984741211
    },
    {
      "gflops": 2803851.53496,
      "accuracy": 43.18000030517578
    },
    {
      "gflops": 2837230.7199,
      "accuracy": 42.959999084472656
    },
    {
      "gflops": 2870609.90484,
      "accuracy": 43.849998474121094
    },
    {
      "gflops": 2903989.08978,
      "accuracy": 44.150001525878906
    },
    {
      "gflops": 2937368.27472,
      "accuracy": 44.369998931884766
    },
    {
      "gflops": 2970747.45966,
      "accuracy": 44.810001373291016
    },
    {
      "gflops": 3004126.6446,
      "accuracy": 45.34000015258789
    },
    {
      "gflops": 3037505.82954,
      "accuracy": 44.16999816894531
    },
    {
      "gflops": 3070885.01448,
      "accuracy": 44.29999923706055
    },
    {
      "gflops": 3104264.19942,
      "accuracy": 44.5
    },
    {
      "gflops": 3137643.38436,
      "accuracy": 45.619998931884766
    },
    {
      "gflops": 3171022.5693,
      "accuracy": 44.18000030517578
    },
    {
      "gflops": 3204401.75424,
      "accuracy": 45.5
    },
    {
      "gflops": 3237780.93918,
      "accuracy": 44.650001525878906
    },
    {
      "gflops": 3271160.12412,
      "accuracy": 44.540000915527344
    },
    {
      "gflops": 3304539.30906,
      "accuracy": 44.939998626708984
    },
    {
      "gflops": 3337918.494,
      "accuracy": 44.75
    }
  ],
  "Fed-S": [
    {
      "gflops": 33379.18494,
      "accuracy": 21.540000915527344
    },
    {
      "gflops": 66758.36988,
      "accuracy": 31.520000457763672
    },
    {
      "gflops": 100137.55482,
      "accuracy": 32.2400016784668
    },
    {
      "gflops": 133516.73976,
      "accuracy": 33.91999816894531
    },
    {
      "gflops": 166895.9247,
      "accuracy": 37.31999969482422
    },
    {
      "gflops": 200275.10964,
      "accuracy": 36.040000915527344
    },
    {
      "gflops": 233654.29458,
      "accuracy": 40.34000015258789
    },
    {
      "gflops": 267033.47952,
      "accuracy": 37.290000915527344
    },
    {
      "gflops": 300412.66446,
      "accuracy": 43.060001373291016
    },
    {
      "gflops": 333791.8494,
      "accuracy": 41.290000915527344
    },
    {
      "gflops": 367171.03434,
      "accuracy": 41.79999923706055
    },
    {
      "gflops": 400550.21928,
      "accuracy": 43.20000076293945
    },
    {
      "gflops": 433929.40422,
      "accuracy": 44.09000015258789
    },
    {
      "gflops": 467308.58916,
      "accuracy": 43.959999084472656
    },
    {
      "gflops": 500687.7741,
      "accuracy": 45.130001068115234
    },
    {
      "gflops": 534066.95904,
      "accuracy": 43.56999969482422
    },
    {
      "gflops": 567446.14398,
      "accuracy": 44.72999954223633
    },
    {
      "gflops": 600825.32892,
      "accuracy": 43.939998626708984
    },
    {
      "gflops": 634204.51386,
      "accuracy": 42.20000076293945
    },
    {
      "gflops": 667583.6988,
      "accuracy": 44.0099983215332
    },
    {
      "gflops": 700962.88374,
      "accuracy": 42.900001525878906
    },
    {
      "gflops": 734342.06868,
      "accuracy": 44.689998626708984
    },
    {
      "gflops": 767721.25362,
      "accuracy": 42.779998779296875
    },
    {
      "gflops": 801100.43856,
      "accuracy": 44.0099983215332
    },
    {
      "gflops": 834479.6235,
      "accuracy": 41.86000061035156
    },
    {
      "gflops": 867858.80844,
      "accuracy": 44.18000030517578
    },
    {
      "gflops": 901237.99338,
      "accuracy": 43.59000015258789
    },
    {
      "gflops": 934617.17832,
      "accuracy": 44.88999938964844
    },
    {
      "gflops": 967996.36326,
      "accuracy": 42.56999969482422
    },
    {
      "gflops": 1001375.5482,
      "accuracy": 43.58000183105469
    },
    {
      "gflops": 1034754.73314,
      "accuracy": 44.470001220703125
    },
    {
      "gflops": 1068133.91808,
      "accuracy": 44.06999969482422
    },
    {
      "gflops": 1101513.10302,
      "accuracy": 43.66999816894531
    },
    {
      "gflops": 1134892.28796,
      "accuracy": 43.58000183105469
    },
    {
      "gflops": 1168271.4729,
      "accuracy": 43.72999954223633
    },
    {
      "gflops": 1201650.65784,
      "accuracy": 43.81999969482422
    },
    {
      "gflops": 1235029.84278,
      "accuracy": 42.97999954223633
    },
    {
      "gflops": 1268409.02772,
      "accuracy": 43.529998779296875
    },
    {
      "gflops": 1301788.21266,
      "accuracy": 43.369998931884766
    },
    {
      "gflops": 1335167.3976,
      "accuracy": 43.22999954223633
    },
    {
      "gflops": 1368546.58254,
      "accuracy": 42.66999816894531
    },
    {
      "gflops": 1401925.76748,
      "accuracy": 45.02000045776367
    },
    {
      "gflops": 1435304.95242,
      "accuracy": 41.61000061035156
    },
    {
      "gflops": 1468684.13736,
      "accuracy": 44.849998474121094
    },
    {
      "gflops": 1502063.3223,
      "accuracy": 44.95000076293945
    },
    {
      "gflops": 1535442.50724,
      "accuracy": 44.31999969482422
    },
    {
      "gflops": 1568821.69218,
      "accuracy": 43.849998474121094
    },
    {
      "gflops": 1602200.87712,
      "accuracy": 43.560001373291016
    },
    {
      "gflops": 1635580.06206,
      "accuracy": 41.459999084472656
    },
    {
      "gflops": 1668959.247,
      "accuracy": 43.13999938964844
    },
    {
      "gflops": 1702338.43194,
      "accuracy": 42.86000061035156
    },
    {
      "gflops": 1735717.61688,
      "accuracy": 42.47999954223633
    },
    {
      "gflops": 1769096.80182,
      "accuracy": 43.31999969482422
    },
    {
      "gflops": 1802475.98676,
      "accuracy": 45.150001525878906
    },
    {
      "gflops": 1835855.1717,
      "accuracy": 43.0
    },
    {
      "gflops": 1869234.35664,
      "accuracy": 43.560001373291016
    },
    {
      "gflops": 1902613.54158,
      "accuracy": 44.15999984741211
    },
    {
      "gflops": 1935992.72652,
      "accuracy": 42.189998626708984
    },
    {
      "gflops": 1969371.91146,
      "accuracy": 43.029998779296875
    },
    {
      "gflops": 2002751.0964,
      "accuracy": 43.0
    },
    {
      "gflops": 2036130.28134,
      "accuracy": 44.619998931884766
    },
    {
      "gflops": 2069509.46628,
      "accuracy": 42.18000030517578
    },
    {
      "gflops": 2102888.65122,
      "accuracy": 43.209999084472656
    },
    {
      "gflops": 2136267.83616,
      "accuracy": 42.93000030517578
    },
    {
      "gflops": 2169647.0211,
      "accuracy": 43.310001373291016
    },
    {
      "gflops": 2203026.20604,
      "accuracy": 44.470001220703125
    },
    {
      "gflops": 2236405.39098,
      "accuracy": 43.63999938964844
    },
    {
      "gflops": 2269784.57592,
      "accuracy": 43.86000061035156
    },
    {
      "gflops": 2303163.76086,
      "accuracy": 42.4900016784668
    },
    {
      "gflops": 2336542.9458,
      "accuracy": 42.880001068115234
    },
    {
      "gflops": 2369922.13074,
      "accuracy": 44.11000061035156
    },
    {
      "gflops": 2403301.31568,
      "accuracy": 43.38999938964844
    },
    {
      "gflops": 2436680.50062,
      "accuracy": 42.349998474121094
    },
    {
      "gflops": 2470059.68556,
      "accuracy": 42.349998474121094
    },
    {
      "gflops": 2503438.8705,
      "accuracy": 42.84000015258789
    },
    {
      "gflops": 2536818.05544,
      "accuracy": 44.470001220703125
    },
    {
      "gflops": 2570197.24038,
      "accuracy": 44.58000183105469
    },
    {
      "gflops": 2603576.42532,
      "accuracy": 43.52000045776367
    },
    {
      "gflops": 2636955.61026,
      "accuracy": 43.959999084472656
    },
    {
      "gflops": 2670334.7952,
      "accuracy": 44.0
    },
    {
      "gflops": 2703713.98014,
      "accuracy": 43.7599983215332
    },
    {
      "gflops": 2737093.16508,
      "accuracy": 44.15999984741211
    },
    {
      "gflops": 2770472.35002,
      "accuracy": 43.95000076293945
    },
    {
      "gflops": 2803851.53496,
      "accuracy": 40.90999984741211
    },
    {
      "gflops": 2837230.7199,
      "accuracy": 44.0
    },
    {
      "gflops": 2870609.90484,
      "accuracy": 44.38999938964844
    },
    {
      "gflops": 2903989.08978,
      "accuracy": 43.58000183105469
    },
    {
      "gflops": 2937368.27472,
      "accuracy": 42.9900016784668
    },
    {
      "gflops": 2970747.45966,
      "accuracy": 43.5
    },
    {
      "gflops": 3004126.6446,
      "accuracy": 43.43000030517578
    },
    {
      "gflops": 3037505.82954,
      "accuracy": 42.61000061035156
    },
    {
      "gflops": 3070885.01448,
      "accuracy": 44.06999969482422
    },
    {
      "gflops": 3104264.19942,
      "accuracy": 44.540000915527344
    },
    {
      "gflops": 3137643.38436,
      "accuracy": 42.13999938964844
    },
    {
      "gflops": 3171022.5693,
      "accuracy": 42.22999954223633
    },
    {
      "gflops": 3204401.75424,
      "accuracy": 44.75
    },
    {
      "gflops": 3237780.93918,
      "accuracy": 44.790000915527344
    },
    {
      "gflops": 3271160.12412,
      "accuracy": 42.599998474121094
    },
    {
      "gflops": 3304539.30906,
      "accuracy": 45.900001525878906
    },
    {
      "gflops": 3337918.494,
      "accuracy": 44.5
    }
  ],
  "FedDU": [
    {
      "gflops": 16689.59247,
      "accuracy": 26.81999969482422
    },
    {
      "gflops": 33379.18494,
      "accuracy": 33.41999816894531
    },
    {
      "gflops": 50068.77741,
      "accuracy": 35.77000045776367
    },
    {
      "gflops": 66758.36988,
      "accuracy": 35.470001220703125
    },
    {
      "gflops": 83447.96235,
      "accuracy": 34.36000061035156
    },
    {
      "gflops": 100137.55482,
      "accuracy": 37.31999969482422
    },
    {
      "gflops": 116827.14729,
      "accuracy": 42.529998779296875
    },
    {
      "gflops": 133516.73976,
      "accuracy": 41.2400016784668
    },
    {
      "gflops": 150206.33223,
      "accuracy": 44.939998626708984
    },
    {
      "gflops": 166895.9247,
      "accuracy": 44.040000915527344
    },
    {
      "gflops": 183585.51717,
      "accuracy": 45.220001220703125
    },
    {
      "gflops": 200275.10964,
      "accuracy": 46.15999984741211
    },
    {
      "gflops": 216964.70211,
      "accuracy": 44.119998931884766
    },
    {
      "gflops": 233654.29458,
      "accuracy": 45.29999923706055
    },
    {
      "gflops": 250343.88705,
      "accuracy": 46.439998626708984
    },
    {
      "gflops": 267033.47952,
      "accuracy": 46.81999969482422
    },
    {
      "gflops": 283723.07199,
      "accuracy": 47.58000183105469
    },
    {
      "gflops": 300412.66446,
      "accuracy": 46.650001525878906
    },
    {
      "gflops": 317102.25693,
      "accuracy": 45.66999816894531
    },
    {
      "gflops": 333791.8494,
      "accuracy": 45.5099983215332
    },
    {
      "gflops": 350481.44187,
      "accuracy": 45.59000015258789
    },
    {
      "gflops": 367171.03434,
      "accuracy": 46.790000915527344
    },
    {
      "gflops": 383860.62681,
      "accuracy": 46.08000183105469
    },
    {
      "gflops": 400550.21928,
      "accuracy": 47.189998626708984
    },
    {
      "gflops": 417239.81175,
      "accuracy": 47.11000061035156
    },
    {
      "gflops": 433929.40422,
      "accuracy": 45.97999954223633
    },
    {
      "gflops": 450618.99669,
      "accuracy": 48.13999938964844
    },
    {
      "gflops": 467308.58916,
      "accuracy": 46.70000076293945
    },
    {
      "gflops": 483998.18163,
      "accuracy": 46.7400016784668
    },
    {
      "gflops": 500687.7741,
      "accuracy": 46.810001373291016
    },
    {
      "gflops": 517377.36657,
      "accuracy": 46.70000076293945
    },
    {
      "gflops": 534066.95904,
      "accuracy": 45.5099983215332
    },
    {
      "gflops": 550756.55151,
      "accuracy": 47.02000045776367
    },
    {
      "gflops": 567446.14398,
      "accuracy": 46.61000061035156
    },
    {
      "gflops": 584135.73645,
      "accuracy": 48.27000045776367
    },
    {
      "gflops": 600825.32892,
      "accuracy": 48.439998626708984
    },
    {
      "gflops": 617514.92139,
      "accuracy": 45.93000030517578
    },
    {
      "gflops": 634204.51386,
      "accuracy": 47.29999923706055
    },
    {
      "gflops": 650894.10633,
      "accuracy": 48.31999969482422
    },
    {
      "gflops": 667583.6988,
      "accuracy": 48.59000015258789
    },
    {
      "gflops": 684273.29127,
      "accuracy": 47.099998474121094
    },
    {
      "gflops": 700962.88374,
      "accuracy": 46.31999969482422
    },
    {
      "gflops": 717652.47621,
      "accuracy": 48.09000015258789
    },
    {
      "gflops": 734342.06868,
      "accuracy": 48.15999984741211
    },
    {
      "gflops": 751031.66115,
      "accuracy": 46.52000045776367
    },
    {
      "gflops": 767721.25362,
      "accuracy": 47.560001373291016
    },
    {
      "gflops": 784410.84609,
      "accuracy": 46.810001373291016
    },
    {
      "gflops": 801100.43856,
      "accuracy": 48.029998779296875
    },
    {
      "gflops": 817790.03103,
      "accuracy": 47.0099983215332
    },
    {
      "gflops": 834479.6235,
      "accuracy": 48.150001525878906
    },
    {
      "gflops": 851169.21597,
      "accuracy": 48.81999969482422
    },
    {
      "gflops": 867858.80844,
      "accuracy": 49.15999984741211
    },
    {
      "gflops": 884548.40091,
      "accuracy": 49.0099983215332
    },
    {
      "gflops": 901237.99338,
      "accuracy": 46.33000183105469
    },
    {
      "gflops": 917927.58585,
      "accuracy": 49.31999969482422
    },
    {
      "gflops": 934617.17832,
      "accuracy": 48.34000015258789
    },
    {
      "gflops": 951306.77079,
      "accuracy": 46.66999816894531
    },
    {
      "gflops": 967996.36326,
      "accuracy": 49.47999954223633
    },
    {
      "gflops": 984685.95573,
      "accuracy": 47.970001220703125
    },
    {
      "gflops": 1001375.5482,
      "accuracy": 46.599998474121094
    },
    {
      "gflops": 1018065.14067,
      "accuracy": 47.9900016784668
    },
    {
      "gflops": 1034754.73314,
      "accuracy": 47.77000045776367
    },
    {
      "gflops": 1051444.32561,
      "accuracy": 48.09000015258789
    },
    {
      "gflops": 1068133.91808,
      "accuracy": 49.38999938964844
    },
    {
      "gflops": 1084823.51055,
      "accuracy": 49.880001068115234
    },
    {
      "gflops": 1101513.10302,
      "accuracy": 48.959999084472656
    },
    {
      "gflops": 1118202.69549,
      "accuracy": 47.90999984741211
    },
    {
      "gflops": 1134892.28796,
      "accuracy": 48.11000061035156
    },
    {
      "gflops": 1151581.88043,
      "accuracy": 49.459999084472656
    },
    {
      "gflops": 1168271.4729,
      "accuracy": 46.91999816894531
    },
    {
      "gflops": 1184961.06537,
      "accuracy": 48.130001068115234
    },
    {
      "gflops": 1201650.65784,
      "accuracy": 50.27000045776367
    },
    {
      "gflops": 1218340.25031,
      "accuracy": 47.189998626708984
    },
    {
      "gflops": 1235029.84278,
      "accuracy": 47.47999954223633
    },
    {
      "gflops": 1251719.43525,
      "accuracy": 50.04999923706055
    },
    {
      "gflops": 1268409.02772,
      "accuracy": 49.970001220703125
    },
    {
      "gflops": 1285098.62019,
      "accuracy": 49.11000061035156
    },
    {
      "gflops": 1301788.21266,
      "accuracy": 49.869998931884766
    },
    {
      "gflops": 1318477.80513,
      "accuracy": 49.189998626708984
    },
    {
      "gflops": 1335167.3976,
      "accuracy": 48.45000076293945
    },
    {
      "gflops": 1351856.99007,
      "accuracy": 47.83000183105469
    },
    {
      "gflops": 1368546.58254,
      "accuracy": 49.13999938964844
    },
    {
      "gflops": 1385236.17501,
      "accuracy": 47.310001373291016
    },
    {
      "gflops": 1401925.76748,
      "accuracy": 48.61000061035156
    },
    {
      "gflops": 1418615.35995,
      "accuracy": 48.470001220703125
    },
    {
      "gflops": 1435304.95242,
      "accuracy": 47.41999816894531
    },
    {
      "gflops": 1451994.54489,
      "accuracy": 48.33000183105469
    },
    {
      "gflops": 1468684.13736,
      "accuracy": 47.68000030517578
    },
    {
      "gflops": 1485373.72983,
      "accuracy": 48.33000183105469
    },
    {
      "gflops": 1502063.3223,
      "accuracy": 48.040000915527344
    },
    {
      "gflops": 1518752.91477,
      "accuracy": 49.2599983215332
    },
    {
      "gflops": 1535442.50724,
      "accuracy": 48.790000915527344
    },
    {
      "gflops": 1552132.09971,
      "accuracy": 45.7400016784668
    },
    {
      "gflops": 1568821.69218,
      "accuracy": 48.880001068115234
    },
    {
      "gflops": 1585511.28465,
      "accuracy": 47.709999084472656
    },
    {
      "gflops": 1602200.87712,
      "accuracy": 48.65999984741211
    },
    {
      "gflops": 1618890.46959,
      "accuracy": 47.529998779296875
    },
    {
      "gflops": 1635580.06206,
      "accuracy": 49.70000076293945
    },
    {
      "gflops": 1652269.65453,
      "accuracy": 48.15999984741211
    },
    {
      "gflops": 1668959.247,
      "accuracy": 46.7400016784668
    }
  ],
  "FedATMV": [
    {
      "gflops": 16689.59247,
      "accuracy": 24.31999969482422
    },
    {
      "gflops": 33379.18494,
      "accuracy": 32.779998779296875
    },
    {
      "gflops": 50068.77741,
      "accuracy": 32.119998931884766
    },
    {
      "gflops": 66758.36988,
      "accuracy": 43.52000045776367
    },
    {
      "gflops": 83447.96235,
      "accuracy": 41.099998474121094
    },
    {
      "gflops": 100137.55482,
      "accuracy": 44.93000030517578
    },
    {
      "gflops": 116827.14729,
      "accuracy": 45.97999954223633
    },
    {
      "gflops": 133516.73976,
      "accuracy": 41.45000076293945
    },
    {
      "gflops": 150206.33223,
      "accuracy": 38.529998779296875
    },
    {
      "gflops": 166895.9247,
      "accuracy": 46.68000030517578
    },
    {
      "gflops": 183585.51717,
      "accuracy": 48.06999969482422
    },
    {
      "gflops": 200275.10964,
      "accuracy": 48.13999938964844
    },
    {
      "gflops": 216964.70211,
      "accuracy": 47.779998779296875
    },
    {
      "gflops": 233654.29458,
      "accuracy": 50.310001373291016
    },
    {
      "gflops": 250343.88705,
      "accuracy": 49.0099983215332
    },
    {
      "gflops": 267033.47952,
      "accuracy": 51.189998626708984
    },
    {
      "gflops": 283723.07199,
      "accuracy": 50.220001220703125
    },
    {
      "gflops": 300412.66446,
      "accuracy": 51.939998626708984
    },
    {
      "gflops": 317102.25693,
      "accuracy": 53.380001068115234
    },
    {
      "gflops": 333791.8494,
      "accuracy": 51.84000015258789
    },
    {
      "gflops": 350481.44187,
      "accuracy": 51.88999938964844
    },
    {
      "gflops": 367171.03434,
      "accuracy": 53.029998779296875
    },
    {
      "gflops": 383860.62681,
      "accuracy": 54.189998626708984
    },
    {
      "gflops": 400550.21928,
      "accuracy": 53.380001068115234
    },
    {
      "gflops": 417239.81175,
      "accuracy": 52.59000015258789
    },
    {
      "gflops": 433929.40422,
      "accuracy": 52.65999984741211
    },
    {
      "gflops": 450618.99669,
      "accuracy": 53.400001525878906
    },
    {
      "gflops": 467308.58916,
      "accuracy": 54.0099983215332
    },
    {
      "gflops": 483998.18163,
      "accuracy": 53.689998626708984
    },
    {
      "gflops": 500687.7741,
      "accuracy": 55.29999923706055
    },
    {
      "gflops": 517377.36657,
      "accuracy": 54.619998931884766
    },
    {
      "gflops": 534066.95904,
      "accuracy": 53.040000915527344
    },
    {
      "gflops": 550756.55151,
      "accuracy": 54.060001373291016
    },
    {
      "gflops": 567446.14398,
      "accuracy": 55.31999969482422
    },
    {
      "gflops": 584135.73645,
      "accuracy": 55.33000183105469
    },
    {
      "gflops": 600825.32892,
      "accuracy": 53.810001373291016
    },
    {
      "gflops": 617514.92139,
      "accuracy": 55.709999084472656
    },
    {
      "gflops": 634204.51386,
      "accuracy": 55.56999969482422
    },
    {
      "gflops": 650894.10633,
      "accuracy": 53.20000076293945
    },
    {
      "gflops": 667583.6988,
      "accuracy": 55.560001373291016
    },
    {
      "gflops": 684273.29127,
      "accuracy": 56.369998931884766
    },
    {
      "gflops": 700962.88374,
      "accuracy": 55.18000030517578
    },
    {
      "gflops": 717652.47621,
      "accuracy": 54.65999984741211
    },
    {
      "gflops": 734342.06868,
      "accuracy": 53.20000076293945
    },
    {
      "gflops": 751031.66115,
      "accuracy": 54.209999084472656
    },
    {
      "gflops": 767721.25362,
      "accuracy": 55.790000915527344
    },
    {
      "gflops": 784410.84609,
      "accuracy": 55.040000915527344
    },
    {
      "gflops": 801100.43856,
      "accuracy": 53.130001068115234
    },
    {
      "gflops": 817790.03103,
      "accuracy": 55.150001525878906
    },
    {
      "gflops": 834479.6235,
      "accuracy": 57.0
    },
    {
      "gflops": 851169.21597,
      "accuracy": 55.15999984741211
    },
    {
      "gflops": 867858.80844,
      "accuracy": 56.47999954223633
    },
    {
      "gflops": 884548.40091,
      "accuracy": 55.04999923706055
    },
    {
      "gflops": 901237.99338,
      "accuracy": 55.34000015258789
    },
    {
      "gflops": 917927.58585,
      "accuracy": 54.209999084472656
    },
    {
      "gflops": 934617.17832,
      "accuracy": 55.70000076293945
    },
    {
      "gflops": 951306.77079,
      "accuracy": 54.939998626708984
    },
    {
      "gflops": 967996.36326,
      "accuracy": 53.0
    },
    {
      "gflops": 984685.95573,
      "accuracy": 55.349998474121094
    },
    {
      "gflops": 1001375.5482,
      "accuracy": 54.650001525878906
    },
    {
      "gflops": 1018065.14067,
      "accuracy": 56.45000076293945
    },
    {
      "gflops": 1034754.73314,
      "accuracy": 55.66999816894531
    },
    {
      "gflops": 1051444.32561,
      "accuracy": 55.41999816894531
    },
    {
      "gflops": 1068133.91808,
      "accuracy": 55.45000076293945
    },
    {
      "gflops": 1084823.51055,
      "accuracy": 53.970001220703125
    },
    {
      "gflops": 1101513.10302,
      "accuracy": 55.900001525878906
    },
    {
      "gflops": 1118202.69549,
      "accuracy": 55.4900016784668
    },
    {
      "gflops": 1134892.28796,
      "accuracy": 54.400001525878906
    },
    {
      "gflops": 1151581.88043,
      "accuracy": 53.310001373291016
    },
    {
      "gflops": 1168271.4729,
      "accuracy": 54.75
    },
    {
      "gflops": 1184961.06537,
      "accuracy": 52.84000015258789
    },
    {
      "gflops": 1201650.65784,
      "accuracy": 52.349998474121094
    },
    {
      "gflops": 1218340.25031,
      "accuracy": 54.93000030517578
    },
    {
      "gflops": 1235029.84278,
      "accuracy": 55.16999816894531
    },
    {
      "gflops": 1251719.43525,
      "accuracy": 55.20000076293945
    },
    {
      "gflops": 1268409.02772,
      "accuracy": 52.619998931884766
    },
    {
      "gflops": 1285098.62019,
      "accuracy": 53.38999938964844
    },
    {
      "gflops": 1301788.21266,
      "accuracy": 55.650001525878906
    },
    {
      "gflops": 1318477.80513,
      "accuracy": 55.2599983215332
    },
    {
      "gflops": 1335167.3976,
      "accuracy": 54.630001068115234
    },
    {
      "gflops": 1351856.99007,
      "accuracy": 53.41999816894531
    },
    {
      "gflops": 1368546.58254,
      "accuracy": 51.88999938964844
    },
    {
      "gflops": 1385236.17501,
      "accuracy": 53.310001373291016
    },
    {
      "gflops": 1401925.76748,
      "accuracy": 54.58000183105469
    },
    {
      "gflops": 1418615.35995,
      "accuracy": 55.720001220703125
    },
    {
      "gflops": 1435304.95242,
      "accuracy": 55.58000183105469
    },
    {
      "gflops": 1451994.54489,
      "accuracy": 56.209999084472656
    },
    {
      "gflops": 1468684.13736,
      "accuracy": 58.0099983215332
    },
    {
      "gflops": 1485373.72983,
      "accuracy": 57.43000030517578
    },
    {
      "gflops": 1502063.3223,
      "accuracy": 56.400001525878906
    },
    {
      "gflops": 1518752.91477,
      "accuracy": 57.400001525878906
    },
    {
      "gflops": 1535442.50724,
      "accuracy": 56.83000183105469
    },
    {
      "gflops": 1552132.09971,
      "accuracy": 56.41999816894531
    },
    {
      "gflops": 1568821.69218,
      "accuracy": 55.56999969482422
    },
    {
      "gflops": 1585511.28465,
      "accuracy": 55.91999816894531
    },
    {
      "gflops": 1602200.87712,
      "accuracy": 56.470001220703125
    },
    {
      "gflops": 1618890.46959,
      "accuracy": 54.61000061035156
    },
    {
      "gflops": 1635580.06206,
      "accuracy": 56.84000015258789
    },
    {
      "gflops": 1652269.65453,
      "accuracy": 55.560001373291016
    },
    {
      "gflops": 1668959.247,
      "accuracy": 56.349998474121094
    }
  ],
  "Server-Only": [
    {
      "gflops": 16689.59247,
      "accuracy": 21.940000534057617
    },
    {
      "gflops": 33379.18494,
      "accuracy": 25.170000076293945
    },
    {
      "gflops": 50068.77741,
      "accuracy": 30.18000030517578
    },
    {
      "gflops": 66758.36988,
      "accuracy": 32.16999816894531
    },
    {
      "gflops": 83447.96235,
      "accuracy": 37.95000076293945
    },
    {
      "gflops": 100137.55482,
      "accuracy": 36.20000076293945
    },
    {
      "gflops": 116827.14729,
      "accuracy": 39.83000183105469
    },
    {
      "gflops": 133516.73976,
      "accuracy": 42.220001220703125
    },
    {
      "gflops": 150206.33223,
      "accuracy": 39.099998474121094
    },
    {
      "gflops": 166895.9247,
      "accuracy": 38.209999084472656
    },
    {
      "gflops": 183585.51717,
      "accuracy": 43.90999984741211
    },
    {
      "gflops": 200275.10964,
      "accuracy": 43.369998931884766
    },
    {
      "gflops": 216964.70211,
      "accuracy": 44.0
    },
    {
      "gflops": 233654.29458,
      "accuracy": 44.59000015258789
    },
    {
      "gflops": 250343.88705,
      "accuracy": 42.130001068115234
    },
    {
      "gflops": 267033.47952,
      "accuracy": 44.310001373291016
    },
    {
      "gflops": 283723.07199,
      "accuracy": 42.970001220703125
    },
    {
      "gflops": 300412.66446,
      "accuracy": 43.63999938964844
    },
    {
      "gflops": 317102.25693,
      "accuracy": 44.2400016784668
    },
    {
      "gflops": 333791.8494,
      "accuracy": 43.16999816894531
    },
    {
      "gflops": 350481.44187,
      "accuracy": 43.20000076293945
    },
    {
      "gflops": 367171.03434,
      "accuracy": 44.08000183105469
    },
    {
      "gflops": 383860.62681,
      "accuracy": 43.61000061035156
    },
    {
      "gflops": 400550.21928,
      "accuracy": 42.880001068115234
    },
    {
      "gflops": 417239.81175,
      "accuracy": 43.9900016784668
    },
    {
      "gflops": 433929.40422,
      "accuracy": 43.20000076293945
    },
    {
      "gflops": 450618.99669,
      "accuracy": 42.849998474121094
    },
    {
      "gflops": 467308.58916,
      "accuracy": 43.25
    },
    {
      "gflops": 483998.18163,
      "accuracy": 43.86000061035156
    },
    {
      "gflops": 500687.7741,
      "accuracy": 43.7400016784668
    },
    {
      "gflops": 517377.36657,
      "accuracy": 43.91999816894531
    },
    {
      "gflops": 534066.95904,
      "accuracy": 43.459999084472656
    },
    {
      "gflops": 550756.55151,
      "accuracy": 43.90999984741211
    },
    {
      "gflops": 567446.14398,
      "accuracy": 43.560001373291016
    },
    {
      "gflops": 584135.73645,
      "accuracy": 44.209999084472656
    },
    {
      "gflops": 600825.32892,
      "accuracy": 43.040000915527344
    },
    {
      "gflops": 617514.92139,
      "accuracy": 43.290000915527344
    },
    {
      "gflops": 634204.51386,
      "accuracy": 43.439998626708984
    },
    {
      "gflops": 650894.10633,
      "accuracy": 43.54999923706055
    },
    {
      "gflops": 667583.6988,
      "accuracy": 43.38999938964844
    },
    {
      "gflops": 684273.29127,
      "accuracy": 43.25
    },
    {
      "gflops": 700962.88374,
      "accuracy": 43.22999954223633
    },
    {
      "gflops": 717652.47621,
      "accuracy": 43.65999984741211
    },
    {
      "gflops": 734342.06868,
      "accuracy": 43.5099983215332
    },
    {
      "gflops": 751031.66115,
      "accuracy": 43.619998931884766
    },
    {
      "gflops": 767721.25362,
      "accuracy": 43.47999954223633
    },
    {
      "gflops": 784410.84609,
      "accuracy": 43.68000030517578
    },
    {
      "gflops": 801100.43856,
      "accuracy": 44.16999816894531
    },
    {
      "gflops": 817790.03103,
      "accuracy": 43.540000915527344
    },
    {
      "gflops": 834479.6235,
      "accuracy": 43.5
    },
    {
      "gflops": 851169.21597,
      "accuracy": 43.47999954223633
    },
    {
      "gflops": 867858.80844,
      "accuracy": 43.939998626708984
    },
    {
      "gflops": 884548.40091,
      "accuracy": 42.58000183105469
    },
    {
      "gflops": 901237.99338,
      "accuracy": 43.119998931884766
    },
    {
      "gflops": 917927.58585,
      "accuracy": 42.70000076293945
    },
    {
      "gflops": 934617.17832,
      "accuracy": 42.779998779296875
    },
    {
      "gflops": 951306.77079,
      "accuracy": 42.70000076293945
    },
    {
      "gflops": 967996.36326,
      "accuracy": 43.209999084472656
    },
    {
      "gflops": 984685.95573,
      "accuracy": 42.97999954223633
    },
    {
      "gflops": 1001375.5482,
      "accuracy": 42.779998779296875
    },
    {
      "gflops": 1018065.14067,
      "accuracy": 43.150001525878906
    },
    {
      "gflops": 1034754.73314,
      "accuracy": 43.09000015258789
    },
    {
      "gflops": 1051444.32561,
      "accuracy": 42.459999084472656
    },
    {
      "gflops": 1068133.91808,
      "accuracy": 43.040000915527344
    },
    {
      "gflops": 1084823.51055,
      "accuracy": 40.72999954223633
    },
    {
      "gflops": 1101513.10302,
      "accuracy": 42.77000045776367
    },
    {
      "gflops": 1118202.69549,
      "accuracy": 43.34000015258789
    },
    {
      "gflops": 1134892.28796,
      "accuracy": 42.33000183105469
    },
    {
      "gflops": 1151581.88043,
      "accuracy": 44.04999923706055
    },
    {
      "gflops": 1168271.4729,
      "accuracy": 43.040000915527344
    },
    {
      "gflops": 1184961.06537,
      "accuracy": 43.70000076293945
    },
    {
      "gflops": 1201650.65784,
      "accuracy": 43.349998474121094
    },
    {
      "gflops": 1218340.25031,
      "accuracy": 43.36000061035156
    },
    {
      "gflops": 1235029.84278,
      "accuracy": 43.689998626708984
    },
    {
      "gflops": 1251719.43525,
      "accuracy": 42.77000045776367
    },
    {
      "gflops": 1268409.02772,
      "accuracy": 43.34000015258789
    },
    {
      "gflops": 1285098.62019,
      "accuracy": 43.13999938964844
    },
    {
      "gflops": 1301788.21266,
      "accuracy": 43.369998931884766
    },
    {
      "gflops": 1318477.80513,
      "accuracy": 42.83000183105469
    },
    {
      "gflops": 1335167.3976,
      "accuracy": 42.959999084472656
    },
    {
      "gflops": 1351856.99007,
      "accuracy": 43.220001220703125
    },
    {
      "gflops": 1368546.58254,
      "accuracy": 43.06999969482422
    },
    {
      "gflops": 1385236.17501,
      "accuracy": 42.959999084472656
    },
    {
      "gflops": 1401925.76748,
      "accuracy": 43.41999816894531
    },
    {
      "gflops": 1418615.35995,
      "accuracy": 42.959999084472656
    },
    {
      "gflops": 1435304.95242,
      "accuracy": 43.56999969482422
    },
    {
      "gflops": 1451994.54489,
      "accuracy": 43.369998931884766
    },
    {
      "gflops": 1468684.13736,
      "accuracy": 43.189998626708984
    },
    {
      "gflops": 1485373.72983,
      "accuracy": 43.720001220703125
    },
    {
      "gflops": 1502063.3223,
      "accuracy": 43.2599983215332
    },
    {
      "gflops": 1518752.91477,
      "accuracy": 43.279998779296875
    },
    {
      "gflops": 1535442.50724,
      "accuracy": 42.900001525878906
    },
    {
      "gflops": 1552132.09971,
      "accuracy": 43.439998626708984
    },
    {
      "gflops": 1568821.69218,
      "accuracy": 43.209999084472656
    },
    {
      "gflops": 1585511.28465,
      "accuracy": 42.459999084472656
    },
    {
      "gflops": 1602200.87712,
      "accuracy": 43.68000030517578
    },
    {
      "gflops": 1618890.46959,
      "accuracy": 43.15999984741211
    },
    {
      "gflops": 1635580.06206,
      "accuracy": 43.220001220703125
    },
    {
      "gflops": 1652269.65453,
      "accuracy": 42.9900016784668
    },
    {
      "gflops": 1668959.247,
      "accuracy": 43.029998779296875
    }
  ]
}